i2b2rls/__init__.py
i2b2rls/cli.py
i2b2rls/conf.py
i2b2rls/datasource.py
i2b2rls/i2b2fire.py
i2b2rls/project.py
i2b2rls/role.py
i2b2rls/tables.json
i2b2rls/user.py
i2b2rls/utils.py
i2b2rls/config.default/i2b2.yaml
i2b2rls/config.default/template-ds.xml
i2b2rls/config.default/datasources/rls-ds.xml
i2b2rls/config.default/roles/example/drop.sql
i2b2rls/config.default/roles/example/init.sql
i2b2rls/config.default/roles/example/main.sql
i2b2rls/config.default/roles/example/rls.sql
i2b2rls/config.default/roles/example/test.sql
i2b2rls/config.default/roles/template/main.sql
i2b2rls-0.0.5.dist-info/LICENSE
i2b2rls-0.0.5.dist-info/METADATA
i2b2rls-0.0.5.dist-info/WHEEL
i2b2rls-0.0.5.dist-info/entry_points.txt
i2b2rls-0.0.5.dist-info/top_level.txt
i2b2rls-0.0.5.dist-info/RECORD
