Metadata-Version: 2.1
Name: i2b2rls
Version: 0.0.5
Summary: i2b2 user management with PostgreSQL Row Level Security
Home-page: https://gitlab.com/mds-imbi-freiburg/i2b2/i2b2rls
Author: Fabian Thomczyk
Author-email: fabian.thomczyk@uniklinik-freiburg.de
License: License :: MIT License
Requires-Python: >=3.6
License-File: LICENSE
Requires-Dist: sqlalchemy
Requires-Dist: psycopg2-binary
Requires-Dist: fire
Requires-Dist: automapdb (==0.1.5)
